control2020/__init__.py
control2020/design.py
control2020/heuristics.py
control2020/core/__init__.py
control2020/core/analysis.py
control2020/core/basics.py
control2020/core/root_locus.py
control2020/design/__init__.py
control2020/design/compensator_root_locus.py
control2020/design/pid_root_locus.py
control2020/design/frequency/__init__.py
control2020/design/frequency/analytic.py
control2020/design/frequency/lag.py
control2020/design/frequency/lead.py
control2020/design/frequency/pid.py
control2020/design/frequency/requeriments.py
control2020/design/frequency/stady_state_error.py
control2020/design/statespace/__init__.py
control2020/design/statespace/pi_pole_placement.py
control2020/design/statespace/regulator.py
control2020/design/statespace/tracker.py
craft/__init__.py
craft/app_base.py
craft/layout.py
craft/main.py
craft/templates.py
craft/utils.py
craft/labo/__init__.py
craft/labo/experiment.py
craft/labo/systems.py
craft/principal/__init__.py
control2020-0.0.13.dist-info/METADATA
control2020-0.0.13.dist-info/WHEEL
control2020-0.0.13.dist-info/top_level.txt
control2020-0.0.13.dist-info/RECORD
