Metadata-Version: 2.1
Name: control2020
Version: 0.0.13
Summary: A toolkit to design and lear about control systems
Home-page: https://github.com/bregydoc/controlsystems2020
Author: Bregy Malpartida
Author-email: bregy.malpartida@utec.edu.pe
License: UNKNOWN
Platform: UNKNOWN
Classifier: Programming Language :: Python :: 3
Classifier: License :: OSI Approved :: MIT License
Classifier: Operating System :: OS Independent
Requires-Python: >=3.6
